{
    "check_runs": [
        {
            "id": 78786646721,
            "name": "snyk-frontend",
            "conclusion": "failure",
            "output": {
                "title": "Snyk check failed",
                "summary": "Process completed with exit code 2.",
                "annotations_url": "https://api.github.com/repos/mendsec/catnet_scanner/check-runs/78786646721/annotations"
            }
        },
        {
            "id": 78786646720,
            "name": "snyk-go",
            "conclusion": "failure",
            "output": {
                "title": "Snyk check failed",
                "summary": "Process completed with exit code 2.",
                "annotations_url": "https://api.github.com/repos/mendsec/catnet_scanner/check-runs/78786646720/annotations"
            }
        }
    ]
}
